passwordguard/__init__.py
passwordguard/passwordguard.py
passwordguard-2.0.dist-info/METADATA
passwordguard-2.0.dist-info/WHEEL
passwordguard-2.0.dist-info/top_level.txt
passwordguard-2.0.dist-info/RECORD
