Metadata-Version: 2.1
Name: passwordguard
Version: 2.0
Summary: passwordguard: A library for evaluating password strength and estimating cracking time.
Home-page: https://github.com/Shankhosuvro-G/PasswordGuard
Author: Shankhosuvro Ghosh
Author-email: shankhosuvro.ghosh@gmail.com
Classifier: Programming Language :: Python :: 3
Classifier: License :: OSI Approved :: MIT License
Classifier: Operating System :: OS Independent
Classifier: Intended Audience :: Developers
Classifier: Topic :: Security
Classifier: Topic :: Software Development :: Libraries :: Python Modules
Requires-Python: >=3.6
